Metadata-Version: 2.1
Name: wandbbq
Version: 0.0.2
Summary: Wandb Backup and Quit - Unleash the power of wandb without fear of losing your data
Home-page: https://github.com/mbosc/wandbbq
Author: Matteo Boschini
Author-email: matteoboschini3@gmail.com
License: MIT
Download-URL: https://github.com/mbosc/wandbbq/archive/refs/tags/v0.0.2.zip
Keywords: wandb,bbq,offline,python,utility
Platform: UNKNOWN
Classifier: Development Status :: 3 - Alpha
Classifier: Intended Audience :: Developers
Classifier: Topic :: Software Development :: Build Tools
Classifier: License :: OSI Approved :: MIT License
Classifier: Programming Language :: Python :: 3
Classifier: Programming Language :: Python :: 3.7
Classifier: Programming Language :: Python :: 3.8
Classifier: Programming Language :: Python :: 3.9
License-File: LICENSE.txt
